<annotation>
	<folder>voc2007</folder>
	<filename>2.jpg</filename>
	<path>C:\Users\Administrator\Desktop\电力设备数据集\voc2007\2.jpg</path>
	<source>
		<database>Unknown</database>
	</source>
	<size>
		<width>1706</width>
		<height>1280</height>
		<depth>3</depth>
	</size>
	<segmented>0</segmented>
	<object>
		<name>Circuit-breaker</name>
		<pose>Unspecified</pose>
		<truncated>0</truncated>
		<difficult>0</difficult>
		<bndbox>
			<xmin>653</xmin>
			<ymin>14</ymin>
			<xmax>816</xmax>
			<ymax>923</ymax>
		</bndbox>
	</object>
	<object>
		<name>Circuit-breaker</name>
		<pose>Unspecified</pose>
		<truncated>0</truncated>
		<difficult>0</difficult>
		<bndbox>
			<xmin>860</xmin>
			<ymin>270</ymin>
			<xmax>1009</xmax>
			<ymax>978</ymax>
		</bndbox>
	</object>
	<object>
		<name>Circuit-breaker</name>
		<pose>Unspecified</pose>
		<truncated>0</truncated>
		<difficult>0</difficult>
		<bndbox>
			<xmin>1017</xmin>
			<ymin>431</ymin>
			<xmax>1123</xmax>
			<ymax>1011</ymax>
		</bndbox>
	</object>
	<object>
		<name>Disconnecting link</name>
		<pose>Unspecified</pose>
		<truncated>0</truncated>
		<difficult>0</difficult>
		<bndbox>
			<xmin>83</xmin>
			<ymin>690</ymin>
			<xmax>401</xmax>
			<ymax>1007</ymax>
		</bndbox>
	</object>
	<object>
		<name>Disconnecting link</name>
		<pose>Unspecified</pose>
		<truncated>0</truncated>
		<difficult>0</difficult>
		<bndbox>
			<xmin>387</xmin>
			<ymin>775</ymin>
			<xmax>635</xmax>
			<ymax>1033</ymax>
		</bndbox>
	</object>
</annotation>
